metaclonotypist/__init__.py
metaclonotypist/main.py
metaclonotypist-1.0.1.dist-info/licenses/LICENSE
metaclonotypist-1.0.1.dist-info/METADATA
metaclonotypist-1.0.1.dist-info/WHEEL
metaclonotypist-1.0.1.dist-info/entry_points.txt
metaclonotypist-1.0.1.dist-info/top_level.txt
metaclonotypist-1.0.1.dist-info/RECORD
