Metadata-Version: 2.4
Name: metaclonotypist
Version: 1.0.1
Summary: Metaclonotype discovery pipeline
Author-email: Andreas Tiffeau-Mayer <qimmuno@gmail.com>
Maintainer-email: Andreas Tiffeau-Mayer <qimmuno@gmail.com>
License-Expression: MIT
Project-URL: Homepage, https://github.com/qimmuno/metaclonotypist
Project-URL: Bug Reports, https://github.com/qimmuno/metaclonotypist/issues
Keywords: TCR repertoire,immunology,clustering
Classifier: Development Status :: 5 - Production/Stable
Classifier: Intended Audience :: Developers
Classifier: Topic :: Software Development :: Build Tools
Classifier: Programming Language :: Python :: 3
Classifier: Programming Language :: Python :: 3.9
Classifier: Programming Language :: Python :: 3.10
Classifier: Programming Language :: Python :: 3.11
Classifier: Programming Language :: Python :: 3.12
Classifier: Programming Language :: Python :: 3.13
Requires-Python: >=3.9
License-File: LICENSE
Requires-Dist: numpy
Requires-Dist: scipy
Requires-Dist: pandas
Requires-Dist: pyrepseq[full]
Requires-Dist: statsmodels
Requires-Dist: matplotlib
Requires-Dist: seaborn
Dynamic: license-file
